{
  "openapi": "3.0.1",
  "info": {
    "title": "Store.Api",
    "version": "1.0"
  },
  "paths": {
    "/api/Category": {
      "post": {
        "tags": [
          "Category"
        ],
        "requestBody": {
          "content": {
            "application/json": {
              "schema": {
                "$ref": "#/components/schemas/CategoryCreateDto"
              }
            },
            "text/json": {
              "schema": {
                "$ref": "#/components/schemas/CategoryCreateDto"
              }
            },
            "application/*+json": {
              "schema": {
                "$ref": "#/components/schemas/CategoryCreateDto"
              }
            }
          }
        },
        "responses": {
          "200": {
            "description": "OK"
          }
        }
      },
      "get": {
        "tags": [
          "Category"
        ],
        "responses": {
          "200": {
            "description": "OK"
          }
        }
      }
    },
    "/api/Category/{categoryId}": {
      "get": {
        "tags": [
          "Category"
        ],
        "parameters": [
          {
            "name": "categoryId",
            "in": "path",
            "required": true,
            "schema": {
              "type": "integer",
              "format": "int32"
            }
          }
        ],
        "responses": {
          "200": {
            "description": "OK"
          }
        }
      },
      "delete": {
        "tags": [
          "Category"
        ],
        "parameters": [
          {
            "name": "categoryId",
            "in": "path",
            "required": true,
            "schema": {
              "type": "integer",
              "format": "int32"
            }
          }
        ],
        "responses": {
          "200": {
            "description": "OK"
          }
        }
      },
      "put": {
        "tags": [
          "Category"
        ],
        "parameters": [
          {
            "name": "categoryId",
            "in": "path",
            "required": true,
            "schema": {
              "type": "integer",
              "format": "int32"
            }
          }
        ],
        "requestBody": {
          "content": {
            "application/json": {
              "schema": {
                "$ref": "#/components/schemas/CategoryUpdateDto"
              }
            },
            "text/json": {
              "schema": {
                "$ref": "#/components/schemas/CategoryUpdateDto"
              }
            },
            "application/*+json": {
              "schema": {
                "$ref": "#/components/schemas/CategoryUpdateDto"
              }
            }
          }
        },
        "responses": {
          "200": {
            "description": "OK"
          }
        }
      }
    },
    "/api/Color": {
      "post": {
        "tags": [
          "Color"
        ],
        "requestBody": {
          "content": {
            "application/json": {
              "schema": {
                "$ref": "#/components/schemas/ColorCreateDto"
              }
            },
            "text/json": {
              "schema": {
                "$ref": "#/components/schemas/ColorCreateDto"
              }
            },
            "application/*+json": {
              "schema": {
                "$ref": "#/components/schemas/ColorCreateDto"
              }
            }
          }
        },
        "responses": {
          "200": {
            "description": "OK"
          }
        }
      },
      "get": {
        "tags": [
          "Color"
        ],
        "responses": {
          "200": {
            "description": "OK"
          }
        }
      }
    },
    "/api/Color/{colorId}": {
      "get": {
        "tags": [
          "Color"
        ],
        "parameters": [
          {
            "name": "colorId",
            "in": "path",
            "required": true,
            "schema": {
              "type": "integer",
              "format": "int32"
            }
          }
        ],
        "responses": {
          "200": {
            "description": "OK"
          }
        }
      },
      "delete": {
        "tags": [
          "Color"
        ],
        "parameters": [
          {
            "name": "colorId",
            "in": "path",
            "required": true,
            "schema": {
              "type": "integer",
              "format": "int32"
            }
          }
        ],
        "responses": {
          "200": {
            "description": "OK"
          }
        }
      },
      "put": {
        "tags": [
          "Color"
        ],
        "parameters": [
          {
            "name": "colorId",
            "in": "path",
            "required": true,
            "schema": {
              "type": "integer",
              "format": "int32"
            }
          }
        ],
        "requestBody": {
          "content": {
            "application/json": {
              "schema": {
                "$ref": "#/components/schemas/ColorUpdateDto"
              }
            },
            "text/json": {
              "schema": {
                "$ref": "#/components/schemas/ColorUpdateDto"
              }
            },
            "application/*+json": {
              "schema": {
                "$ref": "#/components/schemas/ColorUpdateDto"
              }
            }
          }
        },
        "responses": {
          "200": {
            "description": "OK"
          }
        }
      }
    },
    "/api/Size": {
      "post": {
        "tags": [
          "Size"
        ],
        "requestBody": {
          "content": {
            "application/json": {
              "schema": {
                "$ref": "#/components/schemas/SizeCreateDto"
              }
            },
            "text/json": {
              "schema": {
                "$ref": "#/components/schemas/SizeCreateDto"
              }
            },
            "application/*+json": {
              "schema": {
                "$ref": "#/components/schemas/SizeCreateDto"
              }
            }
          }
        },
        "responses": {
          "200": {
            "description": "OK"
          }
        }
      },
      "get": {
        "tags": [
          "Size"
        ],
        "responses": {
          "200": {
            "description": "OK"
          }
        }
      }
    },
    "/api/Size/{sizeId}": {
      "get": {
        "tags": [
          "Size"
        ],
        "parameters": [
          {
            "name": "sizeId",
            "in": "path",
            "required": true,
            "schema": {
              "type": "integer",
              "format": "int32"
            }
          }
        ],
        "responses": {
          "200": {
            "description": "OK"
          }
        }
      },
      "delete": {
        "tags": [
          "Size"
        ],
        "parameters": [
          {
            "name": "sizeId",
            "in": "path",
            "required": true,
            "schema": {
              "type": "integer",
              "format": "int32"
            }
          }
        ],
        "responses": {
          "200": {
            "description": "OK"
          }
        }
      },
      "put": {
        "tags": [
          "Size"
        ],
        "parameters": [
          {
            "name": "sizeId",
            "in": "path",
            "required": true,
            "schema": {
              "type": "integer",
              "format": "int32"
            }
          }
        ],
        "requestBody": {
          "content": {
            "application/json": {
              "schema": {
                "$ref": "#/components/schemas/SizeUpdateDto"
              }
            },
            "text/json": {
              "schema": {
                "$ref": "#/components/schemas/SizeUpdateDto"
              }
            },
            "application/*+json": {
              "schema": {
                "$ref": "#/components/schemas/SizeUpdateDto"
              }
            }
          }
        },
        "responses": {
          "200": {
            "description": "OK"
          }
        }
      }
    },
    "/api/Subcategory": {
      "post": {
        "tags": [
          "Subcategory"
        ],
        "requestBody": {
          "content": {
            "application/json": {
              "schema": {
                "$ref": "#/components/schemas/SubcategoryCreateDto"
              }
            },
            "text/json": {
              "schema": {
                "$ref": "#/components/schemas/SubcategoryCreateDto"
              }
            },
            "application/*+json": {
              "schema": {
                "$ref": "#/components/schemas/SubcategoryCreateDto"
              }
            }
          }
        },
        "responses": {
          "200": {
            "description": "OK"
          }
        }
      },
      "get": {
        "tags": [
          "Subcategory"
        ],
        "responses": {
          "200": {
            "description": "OK"
          }
        }
      }
    },
    "/api/Subcategory/{subcategoryId}": {
      "get": {
        "tags": [
          "Subcategory"
        ],
        "parameters": [
          {
            "name": "subcategoryId",
            "in": "path",
            "required": true,
            "schema": {
              "type": "integer",
              "format": "int32"
            }
          }
        ],
        "responses": {
          "200": {
            "description": "OK"
          }
        }
      },
      "delete": {
        "tags": [
          "Subcategory"
        ],
        "parameters": [
          {
            "name": "subcategoryId",
            "in": "path",
            "required": true,
            "schema": {
              "type": "integer",
              "format": "int32"
            }
          }
        ],
        "responses": {
          "200": {
            "description": "OK"
          }
        }
      },
      "put": {
        "tags": [
          "Subcategory"
        ],
        "parameters": [
          {
            "name": "subcategoryId",
            "in": "path",
            "required": true,
            "schema": {
              "type": "integer",
              "format": "int32"
            }
          }
        ],
        "requestBody": {
          "content": {
            "application/json": {
              "schema": {
                "$ref": "#/components/schemas/SubcategoryUpdateDto"
              }
            },
            "text/json": {
              "schema": {
                "$ref": "#/components/schemas/SubcategoryUpdateDto"
              }
            },
            "application/*+json": {
              "schema": {
                "$ref": "#/components/schemas/SubcategoryUpdateDto"
              }
            }
          }
        },
        "responses": {
          "200": {
            "description": "OK"
          }
        }
      }
    }
  },
  "components": {
    "schemas": {
      "CategoryCreateDto": {
        "required": [
          "name"
        ],
        "type": "object",
        "properties": {
          "name": {
            "maxLength": 20,
            "minLength": 1,
            "type": "string"
          },
          "description": {
            "maxLength": 100,
            "type": "string",
            "nullable": true
          },
          "discountId": {
            "type": "integer",
            "format": "int32",
            "nullable": true
          }
        },
        "additionalProperties": false
      },
      "CategoryUpdateDto": {
        "type": "object",
        "properties": {
          "name": {
            "maxLength": 20,
            "type": "string",
            "nullable": true
          },
          "description": {
            "maxLength": 100,
            "type": "string",
            "nullable": true
          }
        },
        "additionalProperties": false
      },
      "ColorCreateDto": {
        "required": [
          "colorName"
        ],
        "type": "object",
        "properties": {
          "colorName": {
            "maxLength": 20,
            "minLength": 1,
            "type": "string"
          }
        },
        "additionalProperties": false
      },
      "ColorUpdateDto": {
        "type": "object",
        "properties": {
          "colorName": {
            "type": "string",
            "nullable": true
          }
        },
        "additionalProperties": false
      },
      "SizeCreateDto": {
        "required": [
          "name"
        ],
        "type": "object",
        "properties": {
          "name": {
            "maxLength": 20,
            "minLength": 1,
            "type": "string"
          },
          "description": {
            "maxLength": 100,
            "type": "string",
            "nullable": true
          }
        },
        "additionalProperties": false
      },
      "SizeUpdateDto": {
        "type": "object",
        "properties": {
          "name": {
            "maxLength": 20,
            "type": "string",
            "nullable": true
          },
          "description": {
            "maxLength": 100,
            "type": "string",
            "nullable": true
          }
        },
        "additionalProperties": false
      },
      "SubcategoryCreateDto": {
        "required": [
          "categoryId",
          "name"
        ],
        "type": "object",
        "properties": {
          "name": {
            "maxLength": 50,
            "minLength": 1,
            "type": "string"
          },
          "description": {
            "maxLength": 50,
            "type": "string",
            "nullable": true
          },
          "categoryId": {
            "type": "integer",
            "format": "int32"
          },
          "discountId": {
            "type": "integer",
            "format": "int32",
            "nullable": true
          }
        },
        "additionalProperties": false
      },
      "SubcategoryUpdateDto": {
        "type": "object",
        "properties": {
          "name": {
            "maxLength": 50,
            "type": "string",
            "nullable": true
          },
          "description": {
            "maxLength": 50,
            "type": "string",
            "nullable": true
          },
          "categoryId": {
            "type": "integer",
            "format": "int32",
            "nullable": true
          },
          "discountId": {
            "type": "integer",
            "format": "int32",
            "nullable": true
          }
        },
        "additionalProperties": false
      }
    }
  }
}